[{"url": "https://www.163.com/news/article/KR8P077G0001899O.html", "send_time": "04/23/2026 21:53:16"}, {"url": "https://www.163.com/dy/article/KR8N43UP0514D3UH.html", "send_time": "04/23/2026 23:13:21"}, {"url": "https://www.163.com/dy/article/KR80FL3P051492T3.html", "send_time": "04/23/2026 23:13:22"}, {"url": "https://www.163.com/dy/article/KR7TJUKA051492T3.html", "send_time": "04/23/2026 23:13:22"}, {"url": "https://www.163.com/dy/article/KR7NQIQT053469LG.html", "send_time": "04/23/2026 23:23:19"}, {"url": "https://www.163.com/dy/article/KR8UBJPV05345ARG.html", "send_time": "04/23/2026 23:33:20"}, {"url": "https://www.163.com/news/article/KR8V8GBE0001899O.html", "send_time": "04/23/2026 23:43:18"}, {"url": "https://www.163.com/dy/article/KR8TG13M0514R9OJ.html", "send_time": "04/23/2026 23:53:40"}, {"url": "https://www.163.com/dy/article/KR8T5OC00534A4SC.html", "send_time": "04/24/2026 00:03:26"}, {"url": "https://www.163.com/news/article/KR917PED0001899O.html", "send_time": "04/24/2026 00:13:20"}, {"url": "https://www.163.com/dy/article/KR90DKV205345ARG.html", "send_time": "04/24/2026 00:13:20"}, {"url": "https://www.163.com/dy/article/KR9122E4051492LM.html", "send_time": "04/24/2026 01:13:17"}, {"url": "https://www.163.com/dy/article/KR8TE8LL0514R9OJ.html", "send_time": "04/24/2026 01:33:18"}, {"url": "https://www.163.com/dy/article/KR8465LQ0519DDQ2.html", "send_time": "04/24/2026 01:33:19"}, {"url": "https://www.163.com/news/article/KR960Q7Q0001899O.html", "send_time": "04/24/2026 01:53:22"}, {"url": "https://www.163.com/dy/article/KR92Q31N05561G0D.html", "send_time": "04/24/2026 02:13:21"}, {"url": "https://www.163.com/dy/article/KR94Q5BK0550A0OW.html", "send_time": "04/24/2026 02:13:21"}, {"url": "https://www.163.com/dy/article/KR7KLC490512EFR8.html", "send_time": "04/24/2026 02:43:22"}, {"url": "https://www.163.com/dy/article/KR7MK8A00514D3UH.html", "send_time": "04/24/2026 02:43:22"}, {"url": "https://www.163.com/dy/article/KR76QRKC0514R9OJ.html", "send_time": "04/24/2026 02:53:15"}, {"url": "https://www.163.com/dy/article/KR99G25A05561G0D.html", "send_time": "04/24/2026 03:03:41"}, {"url": "https://www.163.com/dy/article/KR9BG7SF051492T3.html", "send_time": "04/24/2026 03:23:18"}, {"url": "https://www.163.com/dy/article/KR98O24A0530JPVV.html", "send_time": "04/24/2026 03:53:18"}, {"url": "https://www.163.com/dy/article/KR9A5J0Q053469LG.html", "send_time": "04/24/2026 04:13:21"}, {"url": "https://www.163.com/dy/article/KR9DG3U8055040N3.html", "send_time": "04/24/2026 04:13:21"}, {"url": "https://www.163.com/dy/article/KR99LDUK0512B07B.html", "send_time": "04/24/2026 04:23:19"}, {"url": "https://www.163.com/dy/article/KR9G08QK05345ARG.html", "send_time": "04/24/2026 04:43:22"}, {"url": "https://www.163.com/dy/article/KR94E4050534A4SC.html", "send_time": "04/24/2026 04:53:20"}, {"url": "https://www.163.com/news/article/KR9HLD720001899O.html", "send_time": "04/24/2026 05:13:17"}, {"url": "https://www.163.com/dy/article/KR9ARQ470550B6IS.html", "send_time": "04/24/2026 05:23:23"}, {"url": "https://www.163.com/news/article/KR9KJ8LD0001899O.html", "send_time": "04/24/2026 05:53:31"}, {"url": "https://www.163.com/dy/article/KR9IE8AQ0534A4SC.html", "send_time": "04/24/2026 06:03:44"}, {"url": "https://www.163.com/dy/article/KR9G33P10514R9P4.html", "send_time": "04/24/2026 06:03:44"}, {"url": "https://www.163.com/dy/article/KR92CD7B0512B07B.html", "send_time": "04/24/2026 06:13:28"}, {"url": "https://www.163.com/news/article/KR9MJCBU0001899O.html", "send_time": "04/24/2026 06:53:27"}, {"url": "https://www.163.com/dy/article/KR9F4CU1051492T3.html", "send_time": "04/24/2026 06:53:27"}, {"url": "https://www.163.com/dy/article/KR9CVKD00519DBFP.html", "send_time": "04/24/2026 07:03:43"}, {"url": "https://www.163.com/dy/article/KR9ND6SG0530JPVV.html", "send_time": "04/24/2026 07:33:40"}, {"url": "https://www.163.com/dy/article/KR9OI92I05561G0D.html", "send_time": "04/24/2026 07:43:36"}, {"url": "https://www.163.com/dy/article/KR9PO05F05561G0D.html", "send_time": "04/24/2026 07:43:36"}, {"url": "https://www.163.com/dy/article/KR9RTHJM055040N3.html", "send_time": "04/24/2026 08:13:27"}, {"url": "https://www.163.com/dy/article/KR9NL40S0512B07B.html", "send_time": "04/24/2026 08:33:39"}, {"url": "https://www.163.com/dy/article/KR9QA8H505561G0D.html", "send_time": "04/24/2026 08:43:28"}, {"url": "https://www.163.com/dy/article/KR9ESB3E05561G0D.html", "send_time": "04/24/2026 08:43:28"}, {"url": "https://www.163.com/dy/article/KR9UEDT60514BE2Q.html", "send_time": "04/24/2026 09:33:27"}, {"url": "https://www.163.com/dy/article/KRA0UIB805561G0D.html", "send_time": "04/24/2026 09:53:23"}]