[{"url": "https://www.163.com/dy/article/L1N8DTR0055080L4.html", "send_time": "07/13/2026 03:13:13"}, {"url": "https://www.163.com/dy/article/L1NBR92B0512BEVO.html", "send_time": "07/13/2026 03:33:14"}, {"url": "https://www.163.com/dy/article/L1NCI44T053469LG.html", "send_time": "07/13/2026 03:53:16"}, {"url": "https://www.163.com/dy/article/L1NCKEJC055040N3.html", "send_time": "07/13/2026 03:53:17"}, {"url": "https://www.163.com/dy/article/L1NDV4UA0512DU6N.html", "send_time": "07/13/2026 04:13:19"}, {"url": "https://www.163.com/dy/article/L1NCLCJ20534A4SC.html", "send_time": "07/13/2026 04:13:19"}, {"url": "https://www.163.com/dy/article/L1NCI3B4053469LG.html", "send_time": "07/13/2026 04:23:15"}, {"url": "https://www.163.com/dy/article/L1NGE4E205345ARG.html", "send_time": "07/13/2026 04:53:16"}, {"url": "https://www.163.com/news/article/L1NHU3F20001899O.html", "send_time": "07/13/2026 05:13:15"}, {"url": "https://www.163.com/dy/article/L1NHMIMP051492T3.html", "send_time": "07/13/2026 05:33:17"}, {"url": "https://www.163.com/dy/article/L1ND5VFN05561G0D.html", "send_time": "07/13/2026 05:43:15"}, {"url": "https://www.163.com/dy/article/L1NEJCUS0550A0OW.html", "send_time": "07/13/2026 06:03:21"}, {"url": "https://www.163.com/news/article/L1NKA66Q0001899O.html", "send_time": "07/13/2026 06:03:21"}, {"url": "https://www.163.com/news/article/L1NLE48I0001899O.html", "send_time": "07/13/2026 06:23:14"}, {"url": "https://www.163.com/dy/article/L1NFFV3T05199DKK.html", "send_time": "07/13/2026 06:43:18"}, {"url": "https://www.163.com/dy/article/L1MVAQB30514BE2Q.html", "send_time": "07/13/2026 07:03:16"}, {"url": "https://www.163.com/dy/article/L1NO4H01053469LG.html", "send_time": "07/13/2026 07:23:19"}, {"url": "https://www.163.com/dy/article/L1NJAIA405506O99.html", "send_time": "07/13/2026 08:03:23"}, {"url": "https://www.163.com/dy/article/L1NKNER405506O99.html", "send_time": "07/13/2026 08:03:24"}, {"url": "https://www.163.com/dy/article/L18FPVEJ0512BN99.html", "send_time": "07/13/2026 08:03:24"}, {"url": "https://www.163.com/news/article/L1NTRTD000019B3E.html", "send_time": "07/13/2026 08:43:15"}, {"url": "https://www.163.com/dy/article/L1NDF19B0514D3UH.html", "send_time": "07/13/2026 08:53:18"}, {"url": "https://www.163.com/dy/article/L1NGB8VP051492LM.html", "send_time": "07/13/2026 09:13:20"}, {"url": "https://www.163.com/news/article/L1O0214E00019B3E.html", "send_time": "07/13/2026 09:13:20"}, {"url": "https://www.163.com/dy/article/L1NT9DGE0514BE2Q.html", "send_time": "07/13/2026 09:13:20"}, {"url": "https://www.163.com/news/article/L1O2944E00019B3E.html", "send_time": "07/13/2026 10:13:20"}, {"url": "https://www.163.com/news/article/L1O249NH00019B3E.html", "send_time": "07/13/2026 10:13:21"}, {"url": "https://www.163.com/dy/article/L1NVBHHF0550B6IS.html", "send_time": "07/13/2026 10:13:21"}, {"url": "https://www.163.com/dy/article/L1O1626G055040N3.html", "send_time": "07/13/2026 10:53:17"}, {"url": "https://www.163.com/dy/article/L1NVP11I051492T3.html", "send_time": "07/13/2026 10:53:17"}, {"url": "https://www.163.com/dy/article/L1NSBN29055040N3.html", "send_time": "07/13/2026 10:53:17"}, {"url": "https://www.163.com/news/article/L1O8UU8G0001899O.html", "send_time": "07/13/2026 11:53:19"}, {"url": "https://www.163.com/dy/article/L1O6H7U20514BE2Q.html", "send_time": "07/13/2026 12:13:18"}, {"url": "https://www.163.com/dy/article/L1NRL46G0550B6IS.html", "send_time": "07/13/2026 12:13:18"}, {"url": "https://www.163.com/dy/article/L1NJRP8S0512DU6N.html", "send_time": "07/13/2026 12:13:18"}, {"url": "https://www.163.com/dy/article/L1NIUJGU05506O99.html", "send_time": "07/13/2026 12:13:18"}, {"url": "https://www.163.com/dy/article/L1NOMG54055040N3.html", "send_time": "07/13/2026 13:13:27"}, {"url": "https://www.163.com/dy/article/L1O3CC910514EGPO.html", "send_time": "07/13/2026 13:13:27"}, {"url": "https://www.163.com/dy/article/L1NNC5M90514EGPO.html", "send_time": "07/13/2026 13:13:28"}, {"url": "https://www.163.com/dy/article/L1O6S43T05561G0D.html", "send_time": "07/13/2026 13:33:24"}, {"url": "https://www.163.com/dy/article/L1O8FA8Q0514BQ68.html", "send_time": "07/13/2026 14:23:26"}, {"url": "https://www.163.com/dy/article/L1O8JT7V053469LG.html", "send_time": "07/13/2026 15:03:21"}, {"url": "https://www.163.com/dy/article/L1O80NR80512B07B.html", "send_time": "07/13/2026 15:03:21"}, {"url": "https://www.163.com/dy/article/L1NOI8QF05561G0D.html", "send_time": "07/13/2026 15:03:21"}]