[{"url": "https://www.163.com/news/article/KAT4VKLK00019B3E.html", "send_time": "10/02/2025 13:30:42"}, {"url": "https://www.163.com/news/article/KAT4L78M00019B3E.html", "send_time": "10/02/2025 13:30:42"}, {"url": "https://www.163.com/news/article/KAT4GAAU00019B3E.html", "send_time": "10/02/2025 13:30:42"}, {"url": "https://www.163.com/dy/article/KAT66ICL0514R9OJ.html", "send_time": "10/02/2025 13:50:37"}, {"url": "https://www.163.com/dy/article/KAT4DKK4053469LG.html", "send_time": "10/02/2025 14:20:40"}, {"url": "https://www.163.com/dy/article/KAT3AC30055040N3.html", "send_time": "10/02/2025 14:20:40"}, {"url": "https://www.163.com/dy/article/KAT023OD051492T3.html", "send_time": "10/02/2025 14:20:40"}, {"url": "https://www.163.com/dy/article/KASPE0FS051492T3.html", "send_time": "10/02/2025 14:40:48"}, {"url": "https://www.163.com/dy/article/KASMPDB40530JPVV.html", "send_time": "10/02/2025 14:40:48"}, {"url": "https://www.163.com/news/article/KATJLG0M0001899O.html", "send_time": "10/02/2025 17:30:42"}, {"url": "https://www.163.com/news/article/KATJJJ430001899O.html", "send_time": "10/02/2025 17:30:43"}, {"url": "https://www.163.com/news/article/KAU1VR6B0001899O.html", "send_time": "10/02/2025 21:40:52"}, {"url": "https://www.163.com/news/article/KAU1KSO80001899O.html", "send_time": "10/02/2025 21:40:52"}, {"url": "https://www.163.com/dy/article/KATF0QFP05504DOQ.html", "send_time": "10/02/2025 23:30:50"}, {"url": "https://www.163.com/dy/article/KAT6PL26053469LG.html", "send_time": "10/02/2025 23:40:49"}, {"url": "https://www.163.com/news/article/KAU9NITJ00019B3E.html", "send_time": "10/03/2025 00:10:54"}, {"url": "https://www.163.com/dy/article/KATBO7JI053469LG.html", "send_time": "10/03/2025 00:21:02"}, {"url": "https://www.163.com/news/article/KAUC94P500019B3E.html", "send_time": "10/03/2025 00:41:07"}, {"url": "https://www.163.com/dy/article/KAUAB5VP053469LG.html", "send_time": "10/03/2025 00:41:07"}, {"url": "https://www.163.com/dy/article/KAUBSDUR0512B07B.html", "send_time": "10/03/2025 01:01:00"}]