[{"url": "https://www.163.com/news/article/K2BQQJ750001899O.html", "send_time": "06/18/2025 09:50:36"}, {"url": "https://www.163.com/dy/article/K2BOJH1O055040N3.html", "send_time": "06/18/2025 10:00:43"}, {"url": "https://www.163.com/dy/article/K2BLFSNT051492T3.html", "send_time": "06/18/2025 10:30:49"}, {"url": "https://www.163.com/dy/article/K2BM7SPL051482MP.html", "send_time": "06/18/2025 10:40:28"}, {"url": "https://www.163.com/news/article/K2BUI9A6000189PS.html", "send_time": "06/18/2025 11:00:29"}, {"url": "https://www.163.com/news/article/K2C1O3G90001899O.html", "send_time": "06/18/2025 12:00:53"}, {"url": "https://www.163.com/dy/article/K2BMPJ7U0514D3UH.html", "send_time": "06/18/2025 12:30:33"}, {"url": "https://www.163.com/dy/article/K2C0TBO0051492T3.html", "send_time": "06/18/2025 12:41:23"}, {"url": "https://www.163.com/dy/article/K2C4P0A305346RC6.html", "send_time": "06/18/2025 13:13:12"}, {"url": "https://www.163.com/dy/article/K2BOJ7H50512B07B.html", "send_time": "06/18/2025 13:31:03"}, {"url": "https://www.163.com/dy/article/K2C7K6GK0514R9OJ.html", "send_time": "06/18/2025 14:01:07"}, {"url": "https://www.163.com/dy/article/K2C9J5770512B07B.html", "send_time": "06/18/2025 14:21:17"}, {"url": "https://www.163.com/dy/article/K2CB5NFK053469LG.html", "send_time": "06/18/2025 15:01:27"}, {"url": "https://www.163.com/dy/article/K2CBVSKD0530JPVV.html", "send_time": "06/18/2025 15:11:06"}, {"url": "https://www.163.com/dy/article/K2BKAMN60514R9P4.html", "send_time": "06/18/2025 20:21:00"}, {"url": "https://www.163.com/dy/article/K2CFMBS30512B07B.html", "send_time": "06/18/2025 20:50:59"}, {"url": "https://www.163.com/news/article/K2D18MJ00001899O.html", "send_time": "06/18/2025 21:00:55"}, {"url": "https://www.163.com/news/article/K2D3PHK10001899O.html", "send_time": "06/18/2025 21:41:19"}]