[{"url": "https://www.163.com/dy/article/KK62UFNH055040N3.html", "send_time": "01/26/2026 01:33:27"}, {"url": "https://www.163.com/dy/article/KK6I19ST0550A0OW.html", "send_time": "01/26/2026 01:53:23"}, {"url": "https://www.163.com/news/article/KK6KC49V0001899O.html", "send_time": "01/26/2026 02:03:26"}, {"url": "https://www.163.com/dy/article/KK6K3P8H0514D3UH.html", "send_time": "01/26/2026 02:13:30"}, {"url": "https://www.163.com/dy/article/KK6H8AJK0514R9OJ.html", "send_time": "01/26/2026 02:23:25"}, {"url": "https://www.163.com/dy/article/KK6KB42305561G0D.html", "send_time": "01/26/2026 02:33:26"}, {"url": "https://www.163.com/dy/article/KK6OGRK805561G0D.html", "send_time": "01/26/2026 03:33:23"}, {"url": "https://www.163.com/dy/article/KK54MUUB051492LM.html", "send_time": "01/26/2026 03:53:26"}, {"url": "https://www.163.com/dy/article/KK5B1JF9053469LG.html", "send_time": "01/26/2026 04:13:25"}, {"url": "https://www.163.com/dy/article/KK6SSFEH051492T3.html", "send_time": "01/26/2026 04:53:23"}, {"url": "https://www.163.com/dy/article/KK6MMFSA0550A0OW.html", "send_time": "01/26/2026 05:03:29"}, {"url": "https://www.163.com/dy/article/KK7264K705346RC6.html", "send_time": "01/26/2026 06:13:25"}, {"url": "https://www.163.com/dy/article/KK6UFFJT05561G0D.html", "send_time": "01/26/2026 06:23:26"}, {"url": "https://www.163.com/dy/article/KK6U04M205345ARG.html", "send_time": "01/26/2026 06:33:22"}, {"url": "https://www.163.com/dy/article/KK71R9S9053469LG.html", "send_time": "01/26/2026 06:43:20"}, {"url": "https://www.163.com/dy/article/KK75HBP80534A4SC.html", "send_time": "01/26/2026 07:13:23"}, {"url": "https://www.163.com/dy/article/KK71544F0530JPVV.html", "send_time": "01/26/2026 07:53:19"}, {"url": "https://www.163.com/dy/article/KK75VJNT053469LG.html", "send_time": "01/26/2026 08:13:23"}, {"url": "https://www.163.com/dy/article/KK777DQG0514R9OJ.html", "send_time": "01/26/2026 08:53:18"}, {"url": "https://www.163.com/news/article/KK7DGHCT0001899O.html", "send_time": "01/26/2026 09:23:27"}, {"url": "https://www.163.com/dy/article/KK77ELCR05561G0D.html", "send_time": "01/26/2026 09:33:20"}, {"url": "https://www.163.com/dy/article/KK7EMGH3051492T3.html", "send_time": "01/26/2026 09:43:22"}, {"url": "https://www.163.com/dy/article/KK7AJ10C0514BE2Q.html", "send_time": "01/26/2026 09:43:22"}, {"url": "https://www.163.com/dy/article/KK7FILJ30514D3UH.html", "send_time": "01/26/2026 09:53:23"}, {"url": "https://www.163.com/dy/article/KK6P8J2P0514R9P4.html", "send_time": "01/26/2026 10:23:25"}, {"url": "https://www.163.com/dy/article/KK7ID5AC053469LG.html", "send_time": "01/26/2026 11:03:20"}, {"url": "https://www.163.com/dy/article/KK7LHEQO0514BE2Q.html", "send_time": "01/26/2026 11:43:22"}, {"url": "https://www.163.com/dy/article/KK7MKC8B053469LG.html", "send_time": "01/26/2026 12:03:28"}, {"url": "https://www.163.com/news/article/KK7ME5CT0001899O.html", "send_time": "01/26/2026 12:03:28"}, {"url": "https://www.163.com/dy/article/KK7KNHR50514BQ68.html", "send_time": "01/26/2026 12:13:27"}, {"url": "https://www.163.com/dy/article/KK6PQP6B0530JPVV.html", "send_time": "01/26/2026 13:13:27"}, {"url": "https://www.163.com/dy/article/KK7F49PQ0530JPVV.html", "send_time": "01/26/2026 13:13:27"}, {"url": "https://www.163.com/dy/article/KK7GTERJ05561G0D.html", "send_time": "01/26/2026 13:23:28"}]