[{"url": "https://www.163.com/dy/article/KQ8OEF9R0512DU6N.html", "send_time": "04/11/2026 11:43:10"}, {"url": "https://www.163.com/news/article/KQ8QK0IV0001899O.html", "send_time": "04/11/2026 12:13:10"}, {"url": "https://www.163.com/news/article/KQ8RE6TC0001899O.html", "send_time": "04/11/2026 12:23:08"}, {"url": "https://www.163.com/news/article/KQ8RASBA0001899O.html", "send_time": "04/11/2026 12:23:08"}, {"url": "https://www.163.com/dy/article/KQ8KUALV0550A0OW.html", "send_time": "04/11/2026 13:23:09"}, {"url": "https://www.163.com/news/article/KQ8VJKJ3000189PS.html", "send_time": "04/11/2026 13:33:12"}, {"url": "https://www.163.com/news/article/KQ90D2U10001899O.html", "send_time": "04/11/2026 13:43:13"}, {"url": "https://www.163.com/dy/article/KQ8KU4UC053469M5.html", "send_time": "04/11/2026 13:53:13"}, {"url": "https://www.163.com/dy/article/KQ8KV80T0550A0OW.html", "send_time": "04/11/2026 14:23:13"}, {"url": "https://www.163.com/dy/article/KQ916J660519D3V1.html", "send_time": "04/11/2026 14:33:18"}, {"url": "https://www.163.com/dy/article/KQ93NF8J053469LG.html", "send_time": "04/11/2026 15:03:14"}, {"url": "https://www.163.com/dy/article/KQ8OM47U0512DU6N.html", "send_time": "04/11/2026 15:03:14"}, {"url": "https://www.163.com/dy/article/KQ9F8CSF05198CJN.html", "send_time": "04/11/2026 18:03:22"}, {"url": "https://www.163.com/news/article/KQ9QROH1000189PS.html", "send_time": "04/11/2026 21:33:14"}, {"url": "https://www.163.com/dy/article/KQ8DNBI905561G0D.html", "send_time": "04/11/2026 23:13:12"}]