[{"url": "https://www.163.com/dy/article/KC671CVM053469LG.html", "send_time": "10/18/2025 12:21:03"}, {"url": "https://www.163.com/news/article/KC67CN3E0001899O.html", "send_time": "10/18/2025 12:21:04"}, {"url": "https://www.163.com/news/article/KC67L3FO0001899O.html", "send_time": "10/18/2025 12:21:04"}, {"url": "https://www.163.com/dy/article/KC65E47H0550B6IS.html", "send_time": "10/18/2025 12:41:07"}, {"url": "https://www.163.com/dy/article/KC689N34055080L4.html", "send_time": "10/18/2025 13:00:59"}, {"url": "https://www.163.com/news/article/KC69VPPO0001899O.html", "send_time": "10/18/2025 13:00:59"}, {"url": "https://www.163.com/dy/article/KC69KK1U0514R9P4.html", "send_time": "10/18/2025 13:21:02"}, {"url": "https://www.163.com/dy/article/KC6BLSA60512B07B.html", "send_time": "10/18/2025 13:31:05"}, {"url": "https://www.163.com/dy/article/KC6C5FPU051492LM.html", "send_time": "10/18/2025 13:41:01"}, {"url": "https://www.163.com/dy/article/KC5QOBGK05561G0D.html", "send_time": "10/18/2025 13:51:05"}, {"url": "https://www.163.com/dy/article/KC6DPPJE051492T3.html", "send_time": "10/18/2025 14:01:06"}, {"url": "https://www.163.com/dy/article/KC3L44UG053469LG.html", "send_time": "10/18/2025 14:01:06"}, {"url": "https://www.163.com/news/article/KC6EGR060001899O.html", "send_time": "10/18/2025 14:11:03"}, {"url": "https://www.163.com/dy/article/KC5RH64T0514BQ68.html", "send_time": "10/18/2025 14:21:08"}, {"url": "https://www.163.com/dy/article/KC6E72R7053469LG.html", "send_time": "10/18/2025 14:31:09"}, {"url": "https://www.163.com/dy/article/KC6CSGOT055080L4.html", "send_time": "10/18/2025 14:31:09"}, {"url": "https://www.163.com/dy/article/KC6ET256053469LG.html", "send_time": "10/18/2025 14:51:02"}, {"url": "https://www.163.com/dy/article/KC6CR9IG0514R9P4.html", "send_time": "10/18/2025 15:01:09"}, {"url": "https://www.163.com/dy/article/KC5E3BJR0514D3UH.html", "send_time": "10/18/2025 15:11:01"}, {"url": "https://www.163.com/news/article/KC7DG39I000189PS.html", "send_time": "10/18/2025 23:51:03"}]