[{"url": "https://www.163.com/dy/article/JREJNT9B0514D3UH.html", "send_time": "03/24/2025 12:10:42"}, {"url": "https://www.163.com/dy/article/JRENRLQH0514D3UH.html", "send_time": "03/24/2025 13:21:12"}, {"url": "https://www.163.com/dy/article/JREO3EJS051492T3.html", "send_time": "03/24/2025 13:31:21"}, {"url": "https://www.163.com/dy/article/JRER0E370512B07B.html", "send_time": "03/24/2025 14:11:17"}, {"url": "https://www.163.com/dy/article/JREQMV880512D3VJ.html", "send_time": "03/24/2025 14:41:11"}, {"url": "https://www.163.com/dy/article/JRFOL18F05198CJN.html", "send_time": "03/24/2025 23:11:07"}, {"url": "https://www.163.com/dy/article/JRF5OJVU0512B07B.html", "send_time": "03/24/2025 23:21:09"}, {"url": "https://www.163.com/dy/article/JRF288700514R9OJ.html", "send_time": "03/24/2025 23:31:14"}]