[{"url": "https://www.163.com/news/article/JPFJ657200019B3E.html", "send_time": "02/28/2025 00:35:37"}, {"url": "https://www.163.com/dy/article/JPFJ9JNB05561G0D.html", "send_time": "02/28/2025 00:55:36"}, {"url": "https://www.163.com/dy/article/JPDNQEKV05504DPG.html", "send_time": "02/28/2025 01:05:33"}, {"url": "https://www.163.com/dy/article/JPFGSTF60514R9OJ.html", "send_time": "02/28/2025 01:25:38"}, {"url": "https://www.163.com/dy/article/JPFM366H0512B07B.html", "send_time": "02/28/2025 01:45:49"}, {"url": "https://www.163.com/dy/article/JPFINDNO055040N3.html", "send_time": "02/28/2025 01:45:49"}, {"url": "https://www.163.com/dy/article/JPFLPLHM0550A0OW.html", "send_time": "02/28/2025 02:05:38"}, {"url": "https://www.163.com/news/article/JPFQIMUF000189PS.html", "send_time": "02/28/2025 02:55:43"}, {"url": "https://www.163.com/dy/article/JPFJTPVD0514R9OJ.html", "send_time": "02/28/2025 02:55:43"}, {"url": "https://www.163.com/news/article/JPFSPDP200019B3E.html", "send_time": "02/28/2025 03:25:42"}, {"url": "https://www.163.com/dy/article/JPFPBBQH0514D9AO.html", "send_time": "02/28/2025 03:25:42"}, {"url": "https://www.163.com/dy/article/JPFDQMN40514R9P4.html", "send_time": "02/28/2025 03:55:35"}, {"url": "https://www.163.com/dy/article/JPFUCVN40530WJTO.html", "send_time": "02/28/2025 04:15:51"}, {"url": "https://www.163.com/news/article/JPG0RSOT0001899O.html", "send_time": "02/28/2025 04:35:37"}, {"url": "https://www.163.com/dy/article/JPFUKEQI0512B07B.html", "send_time": "02/28/2025 04:45:38"}, {"url": "https://www.163.com/news/article/JPG65D6500019B3E.html", "send_time": "02/28/2025 06:05:46"}, {"url": "https://www.163.com/dy/article/JPG5UMB80514BQ68.html", "send_time": "02/28/2025 06:25:51"}, {"url": "https://www.163.com/dy/article/JPG5O445051492T3.html", "send_time": "02/28/2025 06:25:51"}, {"url": "https://www.163.com/dy/article/JPG7T5G10512B07B.html", "send_time": "02/28/2025 06:45:37"}, {"url": "https://www.163.com/news/article/JPG806SK00019B3E.html", "send_time": "02/28/2025 06:45:37"}, {"url": "https://www.163.com/dy/article/JPG9AG91051492T3.html", "send_time": "02/28/2025 07:05:37"}, {"url": "https://www.163.com/news/article/JPGC4FR5000189PS.html", "send_time": "02/28/2025 07:45:35"}, {"url": "https://www.163.com/dy/article/JPG91HOB0514R9OJ.html", "send_time": "02/28/2025 07:45:35"}, {"url": "https://www.163.com/dy/article/JPGD9J600514R9P4.html", "send_time": "02/28/2025 08:15:18"}, {"url": "https://www.163.com/dy/article/JPGA9URF05561G0D.html", "send_time": "02/28/2025 08:35:22"}, {"url": "https://www.163.com/dy/article/JPDMAC460512DU6N.html", "send_time": "02/28/2025 08:45:17"}, {"url": "https://www.163.com/dy/article/JPGAH0FI051492T3.html", "send_time": "02/28/2025 08:55:15"}, {"url": "https://www.163.com/dy/article/JPGFVP200514D3UH.html", "send_time": "02/28/2025 09:25:16"}, {"url": "https://www.163.com/dy/article/JPGM6VPV05561G0D.html", "send_time": "02/28/2025 11:05:27"}, {"url": "https://www.163.com/dy/article/JPGM70E605561G0D.html", "send_time": "02/28/2025 11:15:21"}, {"url": "https://www.163.com/news/article/JPGOKIQP0001899O.html", "send_time": "02/28/2025 12:05:26"}, {"url": "https://www.163.com/dy/article/JPGJQ90K0514R9P4.html", "send_time": "02/28/2025 12:15:21"}, {"url": "https://www.163.com/news/article/JPGRVB7F00019K82.html", "send_time": "02/28/2025 12:25:27"}]