[{"url": "https://www.163.com/dy/article/KKR2418C0512DU6N.html", "send_time": "02/03/2026 00:32:43"}, {"url": "https://www.163.com/dy/article/KKR2D1OL0514D9AO.html", "send_time": "02/03/2026 00:42:41"}, {"url": "https://www.163.com/dy/article/KKR2RDRF053469LG.html", "send_time": "02/03/2026 00:52:36"}, {"url": "https://www.163.com/dy/article/KKR41T5P0514R9OJ.html", "send_time": "02/03/2026 01:32:42"}, {"url": "https://www.163.com/dy/article/KKR7TO7O05561G0D.html", "send_time": "02/03/2026 02:12:41"}, {"url": "https://www.163.com/dy/article/KKPFSDBH051492T3.html", "send_time": "02/03/2026 02:32:37"}, {"url": "https://www.163.com/dy/article/KKQVI9MJ0514BE2Q.html", "send_time": "02/03/2026 03:22:41"}, {"url": "https://www.163.com/dy/article/KKRB87610534A4SC.html", "send_time": "02/03/2026 03:22:41"}, {"url": "https://www.163.com/dy/article/KKRA591O05345ARG.html", "send_time": "02/03/2026 04:02:40"}, {"url": "https://www.163.com/dy/article/KKR51UVQ0550A0OW.html", "send_time": "02/03/2026 04:22:40"}, {"url": "https://www.163.com/dy/article/KKRESIVR0512DU6N.html", "send_time": "02/03/2026 04:22:40"}, {"url": "https://www.163.com/dy/article/KKP21BTD05506O99.html", "send_time": "02/03/2026 05:02:42"}, {"url": "https://www.163.com/news/article/KKRJ9VE00001899O.html", "send_time": "02/03/2026 05:52:38"}, {"url": "https://www.163.com/dy/article/KKRNE7QI0514R9OJ.html", "send_time": "02/03/2026 06:52:40"}, {"url": "https://www.163.com/news/article/KKRO626R0001899O.html", "send_time": "02/03/2026 07:02:38"}, {"url": "https://www.163.com/dy/article/KKROM2NE053469LG.html", "send_time": "02/03/2026 07:12:41"}, {"url": "https://www.163.com/news/article/KKRPIT970001899O.html", "send_time": "02/03/2026 07:22:39"}, {"url": "https://www.163.com/dy/article/KKRMID7J0512B07B.html", "send_time": "02/03/2026 07:42:42"}, {"url": "https://www.163.com/dy/article/KKRQS054055040N3.html", "send_time": "02/03/2026 07:42:42"}, {"url": "https://www.163.com/dy/article/KKRQK4L1053469LG.html", "send_time": "02/03/2026 07:42:42"}, {"url": "https://www.163.com/dy/article/KKRPUHI4053469M5.html", "send_time": "02/03/2026 08:22:41"}, {"url": "https://www.163.com/dy/article/KKRO3RSC053469M5.html", "send_time": "02/03/2026 08:32:40"}, {"url": "https://www.163.com/dy/article/KKRPSU3305345ARG.html", "send_time": "02/03/2026 09:02:45"}, {"url": "https://www.163.com/dy/article/KKRVE6DK05561G0D.html", "send_time": "02/03/2026 09:02:45"}, {"url": "https://www.163.com/dy/article/KKRNEGHA05129QAF.html", "send_time": "02/03/2026 09:12:41"}, {"url": "https://www.163.com/dy/article/KKRVRM1605149SCF.html", "send_time": "02/03/2026 09:42:41"}, {"url": "https://www.163.com/dy/article/KKRU3F9N053469LG.html", "send_time": "02/03/2026 09:52:41"}, {"url": "https://www.163.com/dy/article/KKS05EJH0534A4SC.html", "send_time": "02/03/2026 10:12:41"}, {"url": "https://www.163.com/dy/article/KKS3R7DE0512B07B.html", "send_time": "02/03/2026 10:22:46"}, {"url": "https://www.163.com/dy/article/KKS3IOIT0534P59R.html", "send_time": "02/03/2026 10:32:43"}, {"url": "https://www.163.com/dy/article/KKRUQGS8051492T3.html", "send_time": "02/03/2026 10:52:37"}, {"url": "https://www.163.com/news/article/KKS6ACU80001899O.html", "send_time": "02/03/2026 11:12:41"}, {"url": "https://www.163.com/news/article/KKS7OIHV0001899O.html", "send_time": "02/03/2026 11:42:44"}, {"url": "https://www.163.com/dy/article/KKS3HE8T053469LG.html", "send_time": "02/03/2026 12:12:51"}]