[{"url": "https://www.163.com/dy/article/KNCJEMOL05504DOQ.html", "send_time": "03/07/2026 03:03:07"}, {"url": "https://www.163.com/dy/article/KNCBG8GK0530WJIN.html", "send_time": "03/07/2026 03:03:07"}, {"url": "https://www.163.com/dy/article/KNDQ8IFD051492T3.html", "send_time": "03/07/2026 04:03:10"}, {"url": "https://www.163.com/dy/article/KNDH291H0512B07B.html", "send_time": "03/07/2026 05:33:09"}, {"url": "https://www.163.com/dy/article/KNE02VS70512B07B.html", "send_time": "03/07/2026 05:53:05"}, {"url": "https://www.163.com/news/article/KNE0O3K400019B3E.html", "send_time": "03/07/2026 05:53:05"}, {"url": "https://www.163.com/dy/article/KNE02VR40512B07B.html", "send_time": "03/07/2026 06:03:10"}, {"url": "https://www.163.com/news/article/KNE2J6HP0001899O.html", "send_time": "03/07/2026 06:13:06"}, {"url": "https://www.163.com/dy/article/KNE4LIN905198CJN.html", "send_time": "03/07/2026 07:03:02"}, {"url": "https://www.163.com/dy/article/KNE5DEID0512B07B.html", "send_time": "03/07/2026 07:13:02"}, {"url": "https://www.163.com/dy/article/KNE013HJ055040N3.html", "send_time": "03/07/2026 07:33:06"}, {"url": "https://www.163.com/dy/article/KNDK1F2C05345ARG.html", "send_time": "03/07/2026 07:33:06"}, {"url": "https://www.163.com/news/article/KNE7HAIE0001899O.html", "send_time": "03/07/2026 08:03:10"}, {"url": "https://www.163.com/dy/article/KNEASUNQ0514D3UH.html", "send_time": "03/07/2026 09:12:59"}, {"url": "https://www.163.com/dy/article/KNEDOHBQ055040N3.html", "send_time": "03/07/2026 09:33:06"}, {"url": "https://www.163.com/dy/article/KNEJI9B1053469LG.html", "send_time": "03/07/2026 11:33:16"}, {"url": "https://www.163.com/dy/article/KNDN366K05345ARG.html", "send_time": "03/07/2026 11:53:07"}, {"url": "https://www.163.com/dy/article/KNEMK9AU05346RC6.html", "send_time": "03/07/2026 12:33:17"}, {"url": "https://www.163.com/dy/article/KNEBMJTE053469LG.html", "send_time": "03/07/2026 13:53:10"}, {"url": "https://www.163.com/dy/article/KNESG2JB0512B07B.html", "send_time": "03/07/2026 14:03:14"}, {"url": "https://www.163.com/news/article/KNEUIRN20001899O.html", "send_time": "03/07/2026 14:23:12"}, {"url": "https://www.163.com/dy/article/KNEQHUJ60514R9OJ.html", "send_time": "03/07/2026 14:53:02"}]