[{"url": "https://www.163.com/dy/article/KK01C6VT053469M5.html", "send_time": "01/23/2026 23:13:23"}, {"url": "https://www.163.com/dy/article/KK0E5DCK05504DOQ.html", "send_time": "01/23/2026 23:13:23"}, {"url": "https://www.163.com/dy/article/KK0ENM7K051492LM.html", "send_time": "01/23/2026 23:33:28"}, {"url": "https://www.163.com/dy/article/KK09AF3005561G0D.html", "send_time": "01/23/2026 23:53:28"}, {"url": "https://www.163.com/dy/article/KK0CF8IK0514R9OJ.html", "send_time": "01/23/2026 23:53:29"}, {"url": "https://www.163.com/dy/article/KK06JQK40514R9OJ.html", "send_time": "01/24/2026 00:23:28"}, {"url": "https://www.163.com/dy/article/KK08J3LF05345ARG.html", "send_time": "01/24/2026 00:43:29"}, {"url": "https://www.163.com/dy/article/KJVS1R7O0514R9OJ.html", "send_time": "01/24/2026 00:43:29"}, {"url": "https://www.163.com/dy/article/KK0TIP7V055040N3.html", "send_time": "01/24/2026 01:13:27"}, {"url": "https://www.163.com/news/article/KK1E335Q00019B3E.html", "send_time": "01/24/2026 01:33:30"}, {"url": "https://www.163.com/dy/article/KK1E06PF05561G0D.html", "send_time": "01/24/2026 01:43:27"}, {"url": "https://www.163.com/dy/article/KK1F491T05345ARG.html", "send_time": "01/24/2026 02:13:28"}, {"url": "https://www.163.com/dy/article/KK1FA6PG0512DU6N.html", "send_time": "01/24/2026 02:23:28"}, {"url": "https://www.163.com/dy/article/KK158F1K0514R9OJ.html", "send_time": "01/24/2026 02:43:26"}, {"url": "https://www.163.com/dy/article/KK1G451T05504DOQ.html", "send_time": "01/24/2026 03:03:33"}, {"url": "https://www.163.com/dy/article/KK1FOTFB0530JPVV.html", "send_time": "01/24/2026 03:03:33"}, {"url": "https://www.163.com/dy/article/KK1ERTSB0530JPVV.html", "send_time": "01/24/2026 03:13:33"}, {"url": "https://www.163.com/dy/article/KK18EVDL0514R9P4.html", "send_time": "01/24/2026 03:23:29"}, {"url": "https://www.163.com/dy/article/KK1IVPHQ0514BE2Q.html", "send_time": "01/24/2026 03:43:30"}, {"url": "https://www.163.com/dy/article/KK1LCVR8051492T3.html", "send_time": "01/24/2026 03:53:30"}, {"url": "https://www.163.com/dy/article/KK1JT7SH0530JPVV.html", "send_time": "01/24/2026 04:13:28"}, {"url": "https://www.163.com/dy/article/KK1J8MAG053469LG.html", "send_time": "01/24/2026 04:13:28"}, {"url": "https://www.163.com/dy/article/KK1NL9FI05345ARG.html", "send_time": "01/24/2026 04:43:30"}, {"url": "https://www.163.com/dy/article/KK1NNNIK0512B07B.html", "send_time": "01/24/2026 04:43:30"}, {"url": "https://www.163.com/news/article/KK1TJC680001899O.html", "send_time": "01/24/2026 06:13:35"}, {"url": "https://www.163.com/news/article/KK1U6ESM0001899O.html", "send_time": "01/24/2026 06:23:30"}, {"url": "https://www.163.com/news/article/KK1VJ67500019B3E.html", "send_time": "01/24/2026 06:43:29"}, {"url": "https://www.163.com/news/article/KK1V377C00019B3E.html", "send_time": "01/24/2026 06:43:29"}, {"url": "https://www.163.com/news/article/KK206CCL00019B3E.html", "send_time": "01/24/2026 06:53:29"}]