[{"url": "https://www.163.com/news/article/K0AH9B8U0001899O.html", "send_time": "05/24/2025 01:31:25"}, {"url": "https://www.163.com/dy/article/K0AJA3IQ0514R9OJ.html", "send_time": "05/24/2025 02:01:37"}, {"url": "https://www.163.com/dy/article/K0AGB4E105198CJN.html", "send_time": "05/24/2025 02:11:19"}, {"url": "https://www.163.com/dy/article/K0AB32HJ0514R9P4.html", "send_time": "05/24/2025 02:31:25"}, {"url": "https://www.163.com/dy/article/K0AFG8180514R9OJ.html", "send_time": "05/24/2025 02:41:21"}, {"url": "https://www.163.com/dy/article/K0ALLBIS05129QAF.html", "send_time": "05/24/2025 02:41:22"}, {"url": "https://www.163.com/dy/article/K0AMNSVQ0530JPVV.html", "send_time": "05/24/2025 03:01:24"}, {"url": "https://www.163.com/dy/article/K0AOIFU00514D3UH.html", "send_time": "05/24/2025 04:11:26"}, {"url": "https://www.163.com/dy/article/K0AMBLHS0512D3VJ.html", "send_time": "05/24/2025 04:11:27"}, {"url": "https://www.163.com/dy/article/K0ANG2E8051492T3.html", "send_time": "05/24/2025 04:51:18"}, {"url": "https://www.163.com/dy/article/K0ATBRA50550B6IS.html", "send_time": "05/24/2025 05:01:23"}, {"url": "https://www.163.com/dy/article/K0AP9BDA0550A0OW.html", "send_time": "05/24/2025 05:01:24"}, {"url": "https://www.163.com/dy/article/K0927G9K0550A0OW.html", "send_time": "05/24/2025 05:41:20"}, {"url": "https://www.163.com/dy/article/K0AV9M3T0514R9OJ.html", "send_time": "05/24/2025 05:51:36"}, {"url": "https://www.163.com/dy/article/K09GU3IB051492T3.html", "send_time": "05/24/2025 05:51:36"}, {"url": "https://www.163.com/dy/article/K0999QC70512D03F.html", "send_time": "05/24/2025 06:01:22"}, {"url": "https://www.163.com/dy/article/K0B4HCEK05561G0D.html", "send_time": "05/24/2025 07:00:58"}, {"url": "https://www.163.com/dy/article/K0B2BSUU0550B6IS.html", "send_time": "05/24/2025 07:31:24"}, {"url": "https://www.163.com/dy/article/K0B1VSGI051482MP.html", "send_time": "05/24/2025 07:31:25"}, {"url": "https://www.163.com/dy/article/K0B3K05U0514BQ68.html", "send_time": "05/24/2025 07:31:26"}, {"url": "https://www.163.com/dy/article/K0AQ62VS0534A4SC.html", "send_time": "05/24/2025 07:51:15"}, {"url": "https://www.163.com/dy/article/K0AQ6EPN0514R9OJ.html", "send_time": "05/24/2025 08:21:00"}, {"url": "https://www.163.com/dy/article/K0AJOS680530JPVV.html", "send_time": "05/24/2025 08:31:03"}, {"url": "https://www.163.com/dy/article/K0AVIJ8C0514R9P4.html", "send_time": "05/24/2025 09:11:14"}, {"url": "https://www.163.com/news/article/K0BBVR0F0001899O.html", "send_time": "05/24/2025 09:11:16"}, {"url": "https://www.163.com/dy/article/K0BCSP2R051497H3.html", "send_time": "05/24/2025 09:40:43"}, {"url": "https://www.163.com/dy/article/K0BA83A40514R9OJ.html", "send_time": "05/24/2025 09:40:44"}, {"url": "https://www.163.com/dy/article/K0BDJ44M0550B6IS.html", "send_time": "05/24/2025 10:00:51"}, {"url": "https://www.163.com/dy/article/K0BBO3DP05346RC6.html", "send_time": "05/24/2025 10:20:35"}, {"url": "https://www.163.com/dy/article/K0BIIG800514R9P4.html", "send_time": "05/24/2025 11:40:40"}, {"url": "https://www.163.com/dy/article/K0BGFV8605561G0D.html", "send_time": "05/24/2025 11:50:41"}, {"url": "https://www.163.com/dy/article/K0BKH3G50514R9OJ.html", "send_time": "05/24/2025 11:50:42"}, {"url": "https://www.163.com/dy/article/K0BH4DV9051492T3.html", "send_time": "05/24/2025 12:00:43"}, {"url": "https://www.163.com/dy/article/K0BDM0FA0514R9OJ.html", "send_time": "05/24/2025 12:00:43"}, {"url": "https://www.163.com/dy/article/K0BCSUV305561G0D.html", "send_time": "05/24/2025 12:00:43"}, {"url": "https://www.163.com/news/article/K0BNE8C00001899O.html", "send_time": "05/24/2025 12:20:38"}, {"url": "https://www.163.com/dy/article/K0BCC1H7053469KC.html", "send_time": "05/24/2025 12:20:39"}, {"url": "https://www.163.com/dy/article/K0BJDPCG0514R9OJ.html", "send_time": "05/24/2025 13:00:45"}, {"url": "https://www.163.com/dy/article/K0B8VA7Q0534A4SC.html", "send_time": "05/24/2025 13:00:46"}, {"url": "https://www.163.com/dy/article/K0BMBG7B051482MP.html", "send_time": "05/24/2025 13:20:36"}]