[{"url": "https://www.163.com/dy/article/KG4IQTH00514R9OJ.html", "send_time": "12/06/2025 14:10:59"}, {"url": "https://www.163.com/dy/article/KG4KKSOO053469LG.html", "send_time": "12/06/2025 14:40:47"}, {"url": "https://www.163.com/dy/article/KG41632H051492LM.html", "send_time": "12/06/2025 15:00:54"}, {"url": "https://www.163.com/dy/article/KG4KS2260512B07B.html", "send_time": "12/06/2025 15:00:54"}, {"url": "https://www.163.com/news/article/KG4S4R920001899O.html", "send_time": "12/06/2025 16:40:46"}, {"url": "https://www.163.com/news/article/KG4T2UGR0001899O.html", "send_time": "12/06/2025 16:50:48"}, {"url": "https://www.163.com/dy/article/KG40D4NV0512EFR8.html", "send_time": "12/06/2025 23:30:57"}, {"url": "https://www.163.com/dy/article/KG41ODDP05561G0D.html", "send_time": "12/06/2025 23:40:53"}, {"url": "https://www.163.com/dy/article/KG4OHC2P0512B07B.html", "send_time": "12/06/2025 23:40:53"}, {"url": "https://www.163.com/dy/article/KG3SK9N4051492T3.html", "send_time": "12/07/2025 00:00:54"}, {"url": "https://www.163.com/dy/article/KG4GBHAB0514EGPO.html", "send_time": "12/07/2025 00:20:51"}, {"url": "https://www.163.com/dy/article/KG4CMHCJ0514EGPO.html", "send_time": "12/07/2025 00:50:55"}, {"url": "https://www.163.com/news/article/KG5PH0KS00019B3E.html", "send_time": "12/07/2025 01:20:55"}, {"url": "https://www.163.com/news/article/KG5R7TGU00019B3E.html", "send_time": "12/07/2025 01:40:59"}, {"url": "https://www.163.com/news/article/KG5RN670000189PS.html", "send_time": "12/07/2025 01:50:59"}, {"url": "https://www.163.com/news/article/KG5S26MS00019B3E.html", "send_time": "12/07/2025 02:01:02"}]