[{"url": "https://www.163.com/dy/article/K48QJ4A505345ARG.html", "send_time": "07/12/2025 23:21:23"}, {"url": "https://www.163.com/dy/article/K49I2TKK0512B07B.html", "send_time": "07/12/2025 23:31:19"}, {"url": "https://www.163.com/news/article/K4B4CL070001899O.html", "send_time": "07/12/2025 23:51:23"}, {"url": "https://www.163.com/dy/article/K4B3B8LC0530JPVV.html", "send_time": "07/13/2025 00:01:22"}, {"url": "https://www.163.com/dy/article/K4B52QQK0514R9OJ.html", "send_time": "07/13/2025 00:31:26"}, {"url": "https://www.163.com/dy/article/K4B46N0P0550B6IS.html", "send_time": "07/13/2025 00:31:27"}, {"url": "https://www.163.com/news/article/K4B919H70001899O.html", "send_time": "07/13/2025 01:11:20"}, {"url": "https://www.163.com/news/article/K4B9SCAU0001899O.html", "send_time": "07/13/2025 01:31:21"}, {"url": "https://www.163.com/dy/article/K4B9HVQF0550A0OW.html", "send_time": "07/13/2025 01:41:23"}, {"url": "https://www.163.com/dy/article/K4BAT02D0512B07B.html", "send_time": "07/13/2025 02:01:25"}, {"url": "https://www.163.com/dy/article/K4AC5QTA055040N3.html", "send_time": "07/13/2025 02:41:21"}, {"url": "https://www.163.com/dy/article/K4BD4RV90512DU6N.html", "send_time": "07/13/2025 02:51:21"}, {"url": "https://www.163.com/dy/article/K4BH4F10053469LG.html", "send_time": "07/13/2025 03:41:22"}, {"url": "https://www.163.com/dy/article/K4BH4IMD0514BQ68.html", "send_time": "07/13/2025 04:01:19"}, {"url": "https://www.163.com/dy/article/K4BGLM2M053469LG.html", "send_time": "07/13/2025 04:31:21"}, {"url": "https://www.163.com/dy/article/K4BNPQBO0534P59R.html", "send_time": "07/13/2025 05:31:24"}, {"url": "https://www.163.com/dy/article/K4BNFULM053469M5.html", "send_time": "07/13/2025 05:31:24"}, {"url": "https://www.163.com/news/article/K4BPI7TB0001899O.html", "send_time": "07/13/2025 06:11:35"}, {"url": "https://www.163.com/news/article/K4BPFLP00001899O.html", "send_time": "07/13/2025 06:11:35"}, {"url": "https://www.163.com/dy/article/K4BS43HR0514BE2Q.html", "send_time": "07/13/2025 07:01:35"}, {"url": "https://www.163.com/dy/article/K4BS43S00514BE2Q.html", "send_time": "07/13/2025 07:01:35"}, {"url": "https://www.163.com/dy/article/K4BP8SM90514R9OJ.html", "send_time": "07/13/2025 07:01:35"}, {"url": "https://www.163.com/dy/article/K4BTTSBJ0514R9OJ.html", "send_time": "07/13/2025 07:21:25"}, {"url": "https://www.163.com/dy/article/K4BTN5TP053469LG.html", "send_time": "07/13/2025 07:21:25"}, {"url": "https://www.163.com/dy/article/K4BL3MBP055040N3.html", "send_time": "07/13/2025 07:41:24"}, {"url": "https://www.163.com/dy/article/K4BVV9EC051492T3.html", "send_time": "07/13/2025 07:51:23"}, {"url": "https://www.163.com/news/article/K4BVP67T0001899N.html", "send_time": "07/13/2025 07:51:23"}, {"url": "https://www.163.com/dy/article/K4BVM63L0514TTN3.html", "send_time": "07/13/2025 08:01:28"}, {"url": "https://www.163.com/dy/article/K4BQ4976053469LG.html", "send_time": "07/13/2025 08:11:23"}]