[{"url": "https://www.163.com/dy/article/KPUJ5VUN0514D3UH.html", "send_time": "04/07/2026 15:03:27"}, {"url": "https://www.163.com/dy/article/KPUH885Q051492T3.html", "send_time": "04/07/2026 15:03:27"}, {"url": "https://www.163.com/dy/article/KPU9TQ1K05561G0D.html", "send_time": "04/07/2026 15:03:27"}, {"url": "https://www.163.com/dy/article/KPUEIUMK053469LG.html", "send_time": "04/07/2026 15:03:28"}, {"url": "https://www.163.com/dy/article/KPUE244005199DKK.html", "send_time": "04/07/2026 15:13:17"}, {"url": "https://www.163.com/dy/article/KPUB3RK0053469M5.html", "send_time": "04/07/2026 15:13:17"}, {"url": "https://www.163.com/news/article/KPV42TGG0001899O.html", "send_time": "04/07/2026 17:33:18"}, {"url": "https://www.163.com/news/article/KPV3R61J0001899O.html", "send_time": "04/07/2026 17:33:18"}, {"url": "https://www.163.com/news/article/KPV3J3SP0001899O.html", "send_time": "04/07/2026 17:33:18"}, {"url": "https://www.163.com/news/article/KPV4OK7K0001899O.html", "send_time": "04/07/2026 17:53:07"}, {"url": "https://www.163.com/dy/article/KPVF1MSE05198CJN.html", "send_time": "04/07/2026 21:53:10"}, {"url": "https://www.163.com/dy/article/KPVEMMUK05198CJN.html", "send_time": "04/07/2026 21:53:10"}, {"url": "https://www.163.com/dy/article/KPVADEJP05198CJN.html", "send_time": "04/07/2026 21:53:10"}, {"url": "https://www.163.com/news/article/KPVK57PD0001899O.html", "send_time": "04/07/2026 22:13:07"}, {"url": "https://www.163.com/news/article/KPVNFNGL0001899O.html", "send_time": "04/07/2026 23:13:06"}, {"url": "https://www.163.com/news/article/KPVNNAOP0001899O.html", "send_time": "04/07/2026 23:23:08"}, {"url": "https://www.163.com/news/article/KPVODNG30001899O.html", "send_time": "04/07/2026 23:33:10"}, {"url": "https://www.163.com/news/article/KPVOORV0000189PS.html", "send_time": "04/07/2026 23:43:08"}, {"url": "https://www.163.com/dy/article/KPVPPBSI0534A4SC.html", "send_time": "04/08/2026 00:13:07"}, {"url": "https://www.163.com/dy/article/KPVQO0CN0534A4SC.html", "send_time": "04/08/2026 00:13:07"}, {"url": "https://www.163.com/dy/article/KPVP2B3F0514R9OJ.html", "send_time": "04/08/2026 00:13:07"}, {"url": "https://www.163.com/news/article/KPVSI6J90001899O.html", "send_time": "04/08/2026 00:53:08"}, {"url": "https://www.163.com/dy/article/KPVTBD5G053469LG.html", "send_time": "04/08/2026 01:13:08"}, {"url": "https://www.163.com/dy/article/KPVSM12G053469LG.html", "send_time": "04/08/2026 01:33:09"}, {"url": "https://www.163.com/dy/article/KPVVSIJH0534A4SC.html", "send_time": "04/08/2026 02:13:06"}, {"url": "https://www.163.com/dy/article/KPUPJKT70519875F.html", "send_time": "04/08/2026 02:23:07"}, {"url": "https://www.163.com/dy/article/KQ02TB5J05198CJN.html", "send_time": "04/08/2026 02:53:21"}]