[{"url": "https://www.163.com/dy/article/KE3T9BCK053469LG.html", "send_time": "11/11/2025 12:51:03"}, {"url": "https://www.163.com/dy/article/KE3N1MVH0534P59R.html", "send_time": "11/11/2025 12:51:04"}, {"url": "https://www.163.com/dy/article/KE3LV31Q05345ARG.html", "send_time": "11/11/2025 13:31:05"}, {"url": "https://www.163.com/dy/article/KE3G28MH05568HMT.html", "send_time": "11/11/2025 13:31:05"}, {"url": "https://www.163.com/news/article/KE45I6PA00019B3E.html", "send_time": "11/11/2025 13:41:05"}, {"url": "https://www.163.com/news/article/KE46BK7900019B3E.html", "send_time": "11/11/2025 13:50:57"}, {"url": "https://www.163.com/dy/article/KE41NRSL051482MP.html", "send_time": "11/11/2025 13:50:57"}, {"url": "https://www.163.com/dy/article/KE43S6P00512B07B.html", "send_time": "11/11/2025 14:01:04"}, {"url": "https://www.163.com/dy/article/KE3JE2GJ0512B07B.html", "send_time": "11/11/2025 14:01:04"}, {"url": "https://www.163.com/dy/article/KE17IE5205504DPG.html", "send_time": "11/11/2025 14:11:02"}, {"url": "https://www.163.com/news/article/KE49089V00019B3E.html", "send_time": "11/11/2025 14:41:05"}, {"url": "https://www.163.com/news/article/KE48RKBT00019B3E.html", "send_time": "11/11/2025 14:41:05"}, {"url": "https://www.163.com/dy/article/KE4663S4055080L4.html", "send_time": "11/11/2025 15:01:02"}, {"url": "https://www.163.com/dy/article/KE45LUAH05504DOQ.html", "send_time": "11/11/2025 15:01:02"}, {"url": "https://www.163.com/dy/article/KE4ADLG80514BE2Q.html", "send_time": "11/11/2025 15:20:59"}, {"url": "https://www.163.com/dy/article/KE3TR7MA051492T3.html", "send_time": "11/11/2025 17:40:58"}, {"url": "https://www.163.com/dy/article/KE43ABPO0519DDQ2.html", "send_time": "11/11/2025 23:10:40"}, {"url": "https://www.163.com/dy/article/KE47RV950514R9P4.html", "send_time": "11/11/2025 23:20:42"}, {"url": "https://www.163.com/dy/article/KE17C4O6053469M5.html", "send_time": "11/11/2025 23:20:42"}, {"url": "https://www.163.com/news/article/KE59LKDR0001899O.html", "send_time": "11/12/2025 00:00:43"}, {"url": "https://www.163.com/dy/article/KE56RO5B0514R9OJ.html", "send_time": "11/12/2025 00:00:43"}, {"url": "https://www.163.com/dy/article/KE56LTG00512B07B.html", "send_time": "11/12/2025 00:00:43"}, {"url": "https://www.163.com/dy/article/KE4CC7LL051492T3.html", "send_time": "11/12/2025 00:20:43"}, {"url": "https://www.163.com/dy/article/KE4F1P7S05504DOQ.html", "send_time": "11/12/2025 00:40:38"}, {"url": "https://www.163.com/dy/article/KE5B3R1C051492LM.html", "send_time": "11/12/2025 00:50:39"}]