[{"url": "https://www.163.com/dy/article/KOE5BSHM05198CJN.html", "send_time": "03/19/2026 17:22:47"}, {"url": "https://www.163.com/dy/article/KOEOOGAP0514EGPO.html", "send_time": "03/19/2026 23:22:56"}, {"url": "https://www.163.com/dy/article/KOEOEURR0514R9OJ.html", "send_time": "03/19/2026 23:32:56"}, {"url": "https://www.163.com/dy/article/KOEQ2IKG0534A4SC.html", "send_time": "03/19/2026 23:32:56"}, {"url": "https://www.163.com/news/article/KOERVK580001899O.html", "send_time": "03/19/2026 23:52:55"}, {"url": "https://www.163.com/dy/article/KOEQSISI0512D3VJ.html", "send_time": "03/19/2026 23:52:55"}, {"url": "https://www.163.com/dy/article/KOEQSC6I0512B07B.html", "send_time": "03/20/2026 00:03:03"}, {"url": "https://www.163.com/dy/article/KOCCN6JM0514R9KE.html", "send_time": "03/20/2026 00:22:55"}, {"url": "https://www.163.com/dy/article/KODTVR4C053469LG.html", "send_time": "03/20/2026 00:32:55"}, {"url": "https://www.163.com/dy/article/KODSETGE053469LG.html", "send_time": "03/20/2026 00:42:55"}, {"url": "https://www.163.com/news/article/KOEV5Q2S0001899O.html", "send_time": "03/20/2026 00:52:53"}, {"url": "https://www.163.com/dy/article/KOEOESBT0514R9OJ.html", "send_time": "03/20/2026 01:02:56"}, {"url": "https://www.163.com/dy/article/KOEVPP2H0512B07B.html", "send_time": "03/20/2026 01:02:56"}, {"url": "https://www.163.com/dy/article/KOEUPFN50534A4SC.html", "send_time": "03/20/2026 02:12:53"}, {"url": "https://www.163.com/dy/article/KOERU3LV0514R9P4.html", "send_time": "03/20/2026 02:32:56"}, {"url": "https://www.163.com/dy/article/KOF61FSP05561G0D.html", "send_time": "03/20/2026 03:12:57"}, {"url": "https://www.163.com/dy/article/KOF7CU2605539NA0.html", "send_time": "03/20/2026 03:33:27"}, {"url": "https://www.163.com/dy/article/KOF8ED3S05561G0D.html", "send_time": "03/20/2026 03:43:23"}, {"url": "https://www.163.com/dy/article/KOF0SETT0550A0OW.html", "send_time": "03/20/2026 03:53:21"}, {"url": "https://www.163.com/dy/article/KOF80R9T0519DDQ2.html", "send_time": "03/20/2026 03:53:21"}, {"url": "https://www.163.com/dy/article/KOF97TN90514R9KQ.html", "send_time": "03/20/2026 04:03:31"}, {"url": "https://www.163.com/dy/article/KOFA50SN0552G199.html", "send_time": "03/20/2026 04:13:19"}, {"url": "https://www.163.com/dy/article/KOFALN8F0512D3VJ.html", "send_time": "03/20/2026 04:53:21"}, {"url": "https://www.163.com/dy/article/KOFCTRIR05345ARG.html", "send_time": "03/20/2026 05:03:22"}, {"url": "https://www.163.com/dy/article/KOFE0POE0514BE2Q.html", "send_time": "03/20/2026 05:23:24"}]