[{"url": "https://www.163.com/dy/article/JUQJDBNL055040N3.html", "send_time": "05/05/2025 13:11:16"}, {"url": "https://www.163.com/dy/article/JUQL098U0514BQ68.html", "send_time": "05/05/2025 13:11:17"}, {"url": "https://www.163.com/dy/article/JUQISIVT05346RC6.html", "send_time": "05/05/2025 13:11:17"}, {"url": "https://www.163.com/news/article/JUR00LKG0001899O.html", "send_time": "05/05/2025 14:11:33"}, {"url": "https://www.163.com/news/article/JUR2AAQT0001899O.html", "send_time": "05/05/2025 15:01:23"}, {"url": "https://www.163.com/news/article/JURJT9080001899O.html", "send_time": "05/05/2025 19:51:21"}, {"url": "https://www.163.com/dy/article/JUR5C0EB0514R9OJ.html", "send_time": "05/05/2025 20:11:17"}, {"url": "https://www.163.com/news/article/JUROQGJ80001899O.html", "send_time": "05/05/2025 21:20:31"}, {"url": "https://www.163.com/news/article/JURV68E50001899O.html", "send_time": "05/05/2025 23:10:31"}, {"url": "https://www.163.com/dy/article/JUQGS9HF0514EGPO.html", "send_time": "05/05/2025 23:20:36"}, {"url": "https://www.163.com/dy/article/JURV85K90514R9P4.html", "send_time": "05/05/2025 23:30:35"}, {"url": "https://www.163.com/dy/article/JUS2FVH80514R9OJ.html", "send_time": "05/06/2025 00:20:32"}]