[{"url": "https://www.163.com/dy/article/K5SEDOH60514R9OJ.html", "send_time": "08/01/2025 12:11:17"}, {"url": "https://www.163.com/dy/article/K5ST6O7U053469KC.html", "send_time": "08/01/2025 12:11:17"}, {"url": "https://www.163.com/dy/article/K5TB5HA20514R9OJ.html", "send_time": "08/01/2025 12:21:15"}, {"url": "https://www.163.com/dy/article/K5TCHPHG0519DDQ2.html", "send_time": "08/01/2025 12:41:14"}, {"url": "https://www.163.com/dy/article/K5TCHEEO05345ARG.html", "send_time": "08/01/2025 12:41:14"}, {"url": "https://www.163.com/dy/article/K5T70JQ50534P59R.html", "send_time": "08/01/2025 13:01:15"}, {"url": "https://www.163.com/dy/article/K5T8RLAL051492T3.html", "send_time": "08/01/2025 13:31:18"}, {"url": "https://www.163.com/dy/article/K5TE9KU0051492T3.html", "send_time": "08/01/2025 13:31:18"}, {"url": "https://www.163.com/dy/article/K5TJGIJ205129QAF.html", "send_time": "08/01/2025 14:41:19"}, {"url": "https://www.163.com/dy/article/K5T4LQ8C053469LG.html", "send_time": "08/01/2025 14:41:19"}, {"url": "https://www.163.com/dy/article/K5TEVEI70550HXM1.html", "send_time": "08/01/2025 14:41:19"}, {"url": "https://www.163.com/dy/article/K5T52CP30530JPVV.html", "send_time": "08/01/2025 14:51:17"}, {"url": "https://www.163.com/news/article/K5TM5Q0R0001899O.html", "send_time": "08/01/2025 15:01:24"}, {"url": "https://www.163.com/news/article/K5UJ13LQ0001899O.html", "send_time": "08/01/2025 23:30:48"}, {"url": "https://www.163.com/news/article/K5UIUE8D0001899O.html", "send_time": "08/01/2025 23:30:48"}]