[{"url": "https://www.163.com/dy/article/K1BTSC330512B07B.html", "send_time": "06/06/2025 00:31:22"}, {"url": "https://www.163.com/news/article/K1BTGINS0001899O.html", "send_time": "06/06/2025 00:31:22"}, {"url": "https://www.163.com/news/article/K1BV499M0001899O.html", "send_time": "06/06/2025 00:51:33"}, {"url": "https://www.163.com/news/article/K1C0FKMI0001899O.html", "send_time": "06/06/2025 01:21:15"}, {"url": "https://www.163.com/dy/article/K1C12GN60514R9OJ.html", "send_time": "06/06/2025 01:41:10"}, {"url": "https://www.163.com/news/article/K1C376IG0001899O.html", "send_time": "06/06/2025 02:01:26"}, {"url": "https://www.163.com/news/article/K1C3QDN70001899O.html", "send_time": "06/06/2025 02:11:34"}, {"url": "https://www.163.com/dy/article/K1ABJVR6053469LG.html", "send_time": "06/06/2025 02:41:14"}, {"url": "https://www.163.com/dy/article/K1C5NUF00514R9OJ.html", "send_time": "06/06/2025 02:51:23"}, {"url": "https://www.163.com/dy/article/K1C6J1K9051482MP.html", "send_time": "06/06/2025 03:01:23"}, {"url": "https://www.163.com/news/article/K1C8NL9A0001899O.html", "send_time": "06/06/2025 03:41:15"}, {"url": "https://www.163.com/dy/article/K1BQQNSK0514R9P4.html", "send_time": "06/06/2025 03:41:15"}, {"url": "https://www.163.com/dy/article/K1C9BF350514R9OJ.html", "send_time": "06/06/2025 03:51:13"}, {"url": "https://www.163.com/dy/article/K1CANOKC0514R9P4.html", "send_time": "06/06/2025 04:31:54"}, {"url": "https://www.163.com/dy/article/K1CB3SGG055040N3.html", "send_time": "06/06/2025 04:31:54"}, {"url": "https://www.163.com/dy/article/K1C5V7ET0514R9OJ.html", "send_time": "06/06/2025 04:51:23"}, {"url": "https://www.163.com/news/article/K1CE8THD0001899O.html", "send_time": "06/06/2025 05:11:34"}, {"url": "https://www.163.com/dy/article/K1CCDUMO0514D3UH.html", "send_time": "06/06/2025 05:41:14"}, {"url": "https://www.163.com/news/article/K1CGP6C20001899O.html", "send_time": "06/06/2025 06:01:17"}, {"url": "https://www.163.com/dy/article/K1CFTO7T053469M5.html", "send_time": "06/06/2025 06:11:23"}, {"url": "https://www.163.com/dy/article/K1C7F8P50514BE2Q.html", "send_time": "06/06/2025 06:21:25"}, {"url": "https://www.163.com/dy/article/K1AG9SH10514BE2Q.html", "send_time": "06/06/2025 06:31:43"}, {"url": "https://www.163.com/dy/article/K1CEATDE0550B6IS.html", "send_time": "06/06/2025 06:41:45"}, {"url": "https://www.163.com/news/article/K1CKCDSJ0001899O.html", "send_time": "06/06/2025 07:01:23"}, {"url": "https://www.163.com/dy/article/K1CID6MO0514R9P4.html", "send_time": "06/06/2025 07:11:19"}, {"url": "https://www.163.com/dy/article/K1CIT19M051492T3.html", "send_time": "06/06/2025 07:21:28"}, {"url": "https://www.163.com/dy/article/K1CCJERJ053469LG.html", "send_time": "06/06/2025 07:31:26"}, {"url": "https://www.163.com/dy/article/K1CILIKR0550B6IS.html", "send_time": "06/06/2025 07:51:27"}, {"url": "https://www.163.com/dy/article/K1CNLPFV0514EGPO.html", "send_time": "06/06/2025 08:21:24"}, {"url": "https://www.163.com/dy/article/K1CO3HUB0514D3UH.html", "send_time": "06/06/2025 08:21:24"}, {"url": "https://www.163.com/dy/article/K1CIFBBV05504DOQ.html", "send_time": "06/06/2025 08:31:40"}, {"url": "https://www.163.com/dy/article/K1CQ82L5055040N3.html", "send_time": "06/06/2025 08:51:24"}, {"url": "https://www.163.com/dy/article/K1CQ3P5O0512D03F.html", "send_time": "06/06/2025 09:11:18"}, {"url": "https://www.163.com/news/article/K1CSME4E0001899O.html", "send_time": "06/06/2025 09:31:14"}, {"url": "https://www.163.com/dy/article/K1CQOF3C0514R9P4.html", "send_time": "06/06/2025 09:53:36"}, {"url": "https://www.163.com/dy/article/K1CIC18N0550A0OW.html", "send_time": "06/06/2025 10:21:37"}, {"url": "https://www.163.com/news/article/K1D1D1NK0001899O.html", "send_time": "06/06/2025 10:51:20"}, {"url": "https://www.163.com/dy/article/K1D1505F051492T3.html", "send_time": "06/06/2025 10:51:20"}, {"url": "https://www.163.com/dy/article/K1CP6OU90512B07B.html", "send_time": "06/06/2025 11:01:21"}, {"url": "https://www.163.com/news/article/K1D2FL3N0001899O.html", "send_time": "06/06/2025 11:12:12"}, {"url": "https://www.163.com/news/article/K1D3ETK70001899O.html", "send_time": "06/06/2025 11:41:18"}, {"url": "https://www.163.com/dy/article/K1D42JFC053469KC.html", "send_time": "06/06/2025 12:01:35"}, {"url": "https://www.163.com/news/article/K1D78UI10001899O.html", "send_time": "06/06/2025 12:31:23"}, {"url": "https://www.163.com/dy/article/K1D61TFH0514R9OJ.html", "send_time": "06/06/2025 12:31:23"}]