[{"url": "https://www.163.com/dy/article/KJBJMQEM053469LG.html", "send_time": "01/15/2026 14:33:27"}, {"url": "https://www.163.com/dy/article/KJASRBD60514D3UH.html", "send_time": "01/15/2026 14:43:25"}, {"url": "https://www.163.com/dy/article/KJBBGGL80514D3UH.html", "send_time": "01/15/2026 14:43:25"}, {"url": "https://www.163.com/dy/article/KJBJ3UL1053469LG.html", "send_time": "01/15/2026 14:43:25"}, {"url": "https://www.163.com/dy/article/KJBLVJR805345ARG.html", "send_time": "01/15/2026 14:53:18"}, {"url": "https://www.163.com/news/article/KJBMIT0K0001899O.html", "send_time": "01/15/2026 15:03:28"}, {"url": "https://www.163.com/dy/article/KJBJF9L505345ARG.html", "send_time": "01/15/2026 17:23:26"}, {"url": "https://www.163.com/news/article/KJCDAHT40001899O.html", "send_time": "01/15/2026 21:33:20"}, {"url": "https://www.163.com/dy/article/KJBC6VJ60512B07B.html", "send_time": "01/15/2026 23:23:19"}, {"url": "https://www.163.com/dy/article/KJBL5M8V053469M5.html", "send_time": "01/15/2026 23:33:20"}, {"url": "https://www.163.com/dy/article/KJBH1T4T055040N3.html", "send_time": "01/15/2026 23:53:18"}, {"url": "https://www.163.com/dy/article/KJBOA9FO0514EGPO.html", "send_time": "01/16/2026 00:23:16"}, {"url": "https://www.163.com/dy/article/KJBITBLK05561G0D.html", "send_time": "01/16/2026 00:23:16"}, {"url": "https://www.163.com/news/article/KJCN3MNI00019B3E.html", "send_time": "01/16/2026 00:33:17"}, {"url": "https://www.163.com/dy/article/KJAV0RES05504DOQ.html", "send_time": "01/16/2026 01:03:19"}, {"url": "https://www.163.com/dy/article/KJCH1CC90514R9OJ.html", "send_time": "01/16/2026 01:23:19"}, {"url": "https://www.163.com/dy/article/KJCI7UD50514R9OJ.html", "send_time": "01/16/2026 01:43:18"}, {"url": "https://www.163.com/dy/article/KJBQLGL7051492T3.html", "send_time": "01/16/2026 01:43:18"}, {"url": "https://www.163.com/dy/article/KJCOPVMO05504DOQ.html", "send_time": "01/16/2026 01:53:18"}, {"url": "https://www.163.com/dy/article/KJBOP7QF051492T3.html", "send_time": "01/16/2026 02:13:14"}, {"url": "https://www.163.com/dy/article/KJCRV99D0512DU6N.html", "send_time": "01/16/2026 02:33:17"}]