[{"url": "https://www.163.com/news/article/KE9BL7M20001899O.html", "send_time": "11/13/2025 14:00:45"}, {"url": "https://www.163.com/dy/article/KE9C4O3L053469LG.html", "send_time": "11/13/2025 14:20:40"}, {"url": "https://www.163.com/dy/article/KE9C4NP4053469LG.html", "send_time": "11/13/2025 14:30:44"}, {"url": "https://www.163.com/dy/article/KE96BE7S053469LG.html", "send_time": "11/13/2025 14:30:44"}, {"url": "https://www.163.com/dy/article/KE9KN3SU05504DOQ.html", "send_time": "11/13/2025 17:50:40"}, {"url": "https://www.163.com/dy/article/KE9KGFUP05504DPG.html", "send_time": "11/13/2025 17:50:40"}, {"url": "https://www.163.com/news/article/KE9PVD8C0001899O.html", "send_time": "11/13/2025 18:00:43"}, {"url": "https://www.163.com/news/article/KEA6IT1P0001899O.html", "send_time": "11/13/2025 21:40:41"}, {"url": "https://www.163.com/news/article/KEA6O9960001899O.html", "send_time": "11/13/2025 21:50:39"}, {"url": "https://www.163.com/news/article/KEA8S1970001899O.html", "send_time": "11/13/2025 22:20:38"}, {"url": "https://www.163.com/dy/article/KEAAMQAA0514R9OJ.html", "send_time": "11/13/2025 23:21:09"}, {"url": "https://www.163.com/dy/article/KE9EULE305504DOQ.html", "send_time": "11/13/2025 23:41:10"}, {"url": "https://www.163.com/news/article/KEAE45ON00019B3E.html", "send_time": "11/14/2025 00:01:14"}, {"url": "https://www.163.com/dy/article/KE99JNMF0514D3UH.html", "send_time": "11/14/2025 00:01:14"}, {"url": "https://www.163.com/dy/article/KE9JGHNS0512B07B.html", "send_time": "11/14/2025 00:21:15"}, {"url": "https://www.163.com/dy/article/KE94O3IG0519DDQ2.html", "send_time": "11/14/2025 00:21:15"}, {"url": "https://www.163.com/dy/article/KEAEB93E0512B07B.html", "send_time": "11/14/2025 00:31:08"}, {"url": "https://www.163.com/dy/article/KE93NOQF0514R9P4.html", "send_time": "11/14/2025 00:31:08"}, {"url": "https://www.163.com/dy/article/KE9EMHPS0514EGPO.html", "send_time": "11/14/2025 01:01:09"}, {"url": "https://www.163.com/news/article/KEAIGSGI0001899O.html", "send_time": "11/14/2025 01:11:08"}, {"url": "https://www.163.com/dy/article/KE917LAP051492T3.html", "send_time": "11/14/2025 01:31:12"}]