[{"url": "https://www.163.com/dy/article/K4RSK1A00514R9OJ.html", "send_time": "07/19/2025 12:31:20"}, {"url": "https://www.163.com/dy/article/K4RO3IOF0514BE2Q.html", "send_time": "07/19/2025 12:41:18"}, {"url": "https://www.163.com/dy/article/K4RL32AO053469M5.html", "send_time": "07/19/2025 12:41:18"}, {"url": "https://www.163.com/dy/article/K4RRAK0M05199DKK.html", "send_time": "07/19/2025 13:10:25"}, {"url": "https://www.163.com/dy/article/K4RNSAP50514BE2Q.html", "send_time": "07/19/2025 13:10:25"}, {"url": "https://www.163.com/dy/article/K4RFBGM60512D3VJ.html", "send_time": "07/19/2025 13:10:25"}, {"url": "https://www.163.com/dy/article/K4OLOMQL0514BE2Q.html", "send_time": "07/19/2025 14:30:26"}, {"url": "https://www.163.com/dy/article/K4S0G1H605345ARG.html", "send_time": "07/19/2025 14:50:30"}, {"url": "https://www.163.com/dy/article/K4RULFI305345ARG.html", "send_time": "07/19/2025 14:50:30"}, {"url": "https://www.163.com/dy/article/K4RVKTT50514EGPO.html", "send_time": "07/19/2025 15:10:31"}, {"url": "https://www.163.com/dy/article/K4REII1T0514R9OJ.html", "send_time": "07/19/2025 15:40:36"}, {"url": "https://www.163.com/dy/article/K4S7H4CC053469LG.html", "send_time": "07/19/2025 23:10:43"}, {"url": "https://www.163.com/dy/article/K4S8L6ON0514R9OJ.html", "send_time": "07/19/2025 23:20:45"}, {"url": "https://www.163.com/dy/article/K4S8HN4I055040N3.html", "send_time": "07/19/2025 23:50:45"}, {"url": "https://www.163.com/dy/article/K4MUUIDK053469LG.html", "send_time": "07/20/2025 00:10:41"}]